Depeche/StatusMessage.py
Depeche/StatusUpdater.py
Depeche/__init__.py
depeche-0.0.8.dist-info/licenses/LICENSE
depeche-0.0.8.dist-info/METADATA
depeche-0.0.8.dist-info/WHEEL
depeche-0.0.8.dist-info/top_level.txt
depeche-0.0.8.dist-info/RECORD
