Metadata-Version: 2.4
Name: Depeche
Version: 0.0.8
Summary: A simple message pipeline.
Home-page: https://gitea.com/Lerking/depeche
Author: Jan Lerking
Author-email: 
Classifier: Programming Language :: Python :: 3
Classifier: License :: OSI Approved :: MIT License
Classifier: Operating System :: OS Independent
Requires-Python: >=3.12
License-File: LICENSE
Dynamic: author
Dynamic: classifier
Dynamic: description
Dynamic: description-content-type
Dynamic: home-page
Dynamic: license-file
Dynamic: requires-python
Dynamic: summary
